MANIFEST.in
README.md
requirements.txt
setup.py
sufler/__init__.py
sufler/base.py
sufler/cli.py
sufler.egg-info/PKG-INFO
sufler.egg-info/SOURCES.txt
sufler.egg-info/dependency_links.txt
sufler.egg-info/entry_points.txt
sufler.egg-info/requires.txt
sufler.egg-info/top_level.txt
sufler/__pycache__/__init__.cpython-36.pyc
sufler/__pycache__/base.cpython-36.pyc
sufler/__pycache__/cli.cpython-36.pyc
sufler/backends/__init__.py
sufler/backends/bash/__init__.py
sufler/backends/bash/bash.py
sufler/backends/bash/completer
sufler/backends/fish/__init__.py
sufler/backends/fish/fish.py
sufler/backends/powershell/__init__.py
sufler/backends/powershell/completer
sufler/backends/powershell/powershell.py
sufler/backends/zsh/__init__.py
sufler/backends/zsh/completer
tests/__init__.py
tests/test_backends.py
tests/test_base.py
tests/test_cli.py