Metadata-Version: 1.0
Name: sufler
Version: 0.1.2
Summary: Autocompletion Tool for Bash, Fish, Zsh, PowerShell
Home-page: https://github.com/limebrains/sufler
Author: LimeBrains
Author-email: mail@limebrains.com
License: UNKNOWN
Platform: UNKNOWN
